whl.py
whl-0.0.2.dist-info/METADATA
whl-0.0.2.dist-info/WHEEL
whl-0.0.2.dist-info/RECORD