Metadata-Version: 2.1
Name: whl
Version: 0.0.2
Summary: Minimalist wheel building
